[
  {
    "name": "Ninda Lutfiani, S.Kom, M.T.I",
    "image": "https://aimee.alphabetincubator.id/wp-content/uploads/2022/09/DSCF2487-removebg-preview-e1664282462460-150x150.png",
    "description": "Dosen Universitas Raharja",
    "widuri": "https://widuri.raharja.info/index.php?title=Ninda_Lutfiani",
    "address": "Tangerang"
  },
  {
    "name": "Qurotul Aini, S.Kom., M.T.I",
    "image": "https://aimee.alphabetincubator.id/wp-content/uploads/2022/09/DSCF2475-removebg-preview-e1664283290529-150x150.png",
    "description": "Direktur PT AII",
    "widuri": "https://widuri.raharja.info/index.php?title=Qurotul_Aini",
    "address": "Tangerang"
  },
  {
    "name": "Eka Purnama Harahap, S.Kom, M.T.I",
    "image": "https://aimee.alphabetincubator.id/wp-content/uploads/2022/09/DSCF2488-removebg-preview-e1664268408791-150x150.png",
    "description": "Dosen Universitas Raharja",
    "widuri": "https://widuri.raharja.info/index.php?title=Eka_Purnama_Harahap",
    "address": "Tangerang"
  }
]
